vps_network/__init__.py
vps_network/forms.py
vps_network/resp.py
vps_network/test_ping.py
vps_network/values.py
vps_network/vps_api/__init__.py
vps_network/vps_api/dt.py
vps_network/vps_api/network.py
vps_network/vps_api/test_network.py
vps_network/vps_php/__init__.py
vps_network/vps_php/data_type.py
vps_network/vps_php/do_php.py
vps_network/vps_ping/__init__.py
vps_network/vps_ping/data_type.py
vps_network/vps_ping/do_multi_ping.py
vps_network/vps_ping/print_utils.py
vps_network/vps_quick/__init__.py
vps_network/vps_quick/cli_php_test.py
vps_network/vps_quick/cli_ping_test.py
vps_network/vps_quick/cli_speed_test.py
vps_network/vps_quick/cli_trace_test.py
vps_network/vps_speed/__init__.py
vps_network/vps_speed/data_type.py
vps_network/vps_speed/do_speedtest.py
vps_network/vps_speed/get_list.py
vps_network/vps_speed/utils.py
vps_network/vps_trace/__init__.py
vps_network/vps_trace/data_type.py
vps_network/vps_trace/do_traceroute.py
vps_network/vps_trace/do_traceroute_v2.py
vps_network/vps_utils/__init__.py
vps_network/vps_utils/ip_api.py
vps_network-0.7.0.dist-info/WHEEL
vps_network-0.7.0.dist-info/METADATA
vps_network-0.7.0.dist-info/RECORD
