Metadata-Version: 2.1
Name: vps-network
Version: 0.7.0
Summary: VPS Network Speed Test
Home-page: https://vps.qiyutech.tech/
Author: dev
Author-email: dev@qiyutech.tech
Requires-Python: >=3.9,<4.0
Classifier: Programming Language :: Python :: 3
Classifier: Programming Language :: Python :: 3.9
Requires-Dist: click (>=8,<9)
Requires-Dist: icmplib (>=3.0,<4)
Requires-Dist: ip_api_py (>=0.1,<0.2)
Requires-Dist: pydantic (>=1.7,<2.0)
Requires-Dist: requests (>=2.25,<3)
Requires-Dist: rich (>=10,<11)
Requires-Dist: speedtest-cli (>=2.1,<3)
